AICGRender/AICGRenderInterface.py
AICGRender/__init__.py
AICGRender/pyarmor_runtime_009045/__init__.py
AICGRender/pyarmor_runtime_009045/pyarmor_runtime.so
AICGRender/src/_Convert.py
AICGRender/src/__init__.py
AICGRender/src/colmap_loader.py
AICGRender/src/datastruct.py
AICGRender/src/depth_anything_v2/__init__.py
AICGRender/src/depth_anything_v2/_dpt.py
AICGRender/src/depth_anything_v2/dinov2.py
AICGRender/src/depth_anything_v2/dinov2_layers/__init__.py
AICGRender/src/depth_anything_v2/dinov2_layers/attention.py
AICGRender/src/depth_anything_v2/dinov2_layers/block.py
AICGRender/src/depth_anything_v2/dinov2_layers/drop_path.py
AICGRender/src/depth_anything_v2/dinov2_layers/layer_scale.py
AICGRender/src/depth_anything_v2/dinov2_layers/mlp.py
AICGRender/src/depth_anything_v2/dinov2_layers/patch_embed.py
AICGRender/src/depth_anything_v2/dinov2_layers/swiglu_ffn.py
AICGRender/src/depth_anything_v2/util/__init__.py
AICGRender/src/depth_anything_v2/util/blocks.py
AICGRender/src/depth_anything_v2/util/transform.py
AICGRender/src/outdoor_gaussian/__init__.py
AICGRender/src/outdoor_gaussian/gaussian_reconstruction/__init__.py
AICGRender/src/outdoor_gaussian/gaussian_reconstruction/gaussian_splatting_3d/__init__.py
AICGRender/src/outdoor_gaussian/gaussian_reconstruction/gaussian_splatting_3d/convert.py
AICGRender/src/outdoor_gaussian/gaussian_reconstruction/gaussian_splatting_3d/full_eval.py
AICGRender/src/outdoor_gaussian/gaussian_reconstruction/gaussian_splatting_3d/metrics.py
AICGRender/src/outdoor_gaussian/gaussian_reconstruction/gaussian_splatting_3d/metrics_render.py
AICGRender/src/outdoor_gaussian/gaussian_reconstruction/gaussian_splatting_3d/render.py
AICGRender/src/outdoor_gaussian/gaussian_reconstruction/gaussian_splatting_3d/train.py
AICGRender/src/outdoor_gaussian/gaussian_reconstruction/gaussian_splatting_3d/arguments/__init__.py
AICGRender/src/outdoor_gaussian/gaussian_reconstruction/gaussian_splatting_3d/gaussian_renderer/__init__.py
aicg_model_generation-0.9.0.dist-info/LICENSE
aicg_model_generation-0.9.0.dist-info/METADATA
aicg_model_generation-0.9.0.dist-info/WHEEL
aicg_model_generation-0.9.0.dist-info/top_level.txt
aicg_model_generation-0.9.0.dist-info/RECORD
