Metadata-Version: 2.1
Name: aicg-model-generation
Version: 0.9.0
Summary: new sdf package
Home-page: 
Author: aicg
Author-email: aicg@qq.com
Classifier: Programming Language :: Python :: 3
Classifier: License :: OSI Approved :: MIT License
Classifier: Operating System :: OS Independent
License-File: LICENSE
Requires-Dist: opencv-python
